[{"name":"app","description":null,"location":"index.html","searchKeys":["app"]},{"name":"com.poemgen.mockspire","description":null,"location":"app/com.poemgen.mockspire/index.html","searchKeys":["com.poemgen.mockspire"]},{"name":"MainActivity","description":null,"location":"app/com.poemgen.mockspire/-main-activity/index.html","searchKeys":["MainActivity"]},{"name":"PoemMainFragment","description":null,"location":"app/com.poemgen.mockspire/-poem-main-fragment/index.html","searchKeys":["PoemMainFragment"]},{"name":"com.poemgen.mockspire.model","description":null,"location":"app/com.poemgen.mockspire.model/index.html","searchKeys":["com.poemgen.mockspire.model"]},{"name":"PoemMainViewModel","description":null,"location":"app/com.poemgen.mockspire.model/-poem-main-view-model/index.html","searchKeys":["PoemMainViewModel"]},{"name":"com.poemgen.mockspire.poemgenerator","description":null,"location":"app/com.poemgen.mockspire.poemgenerator/index.html","searchKeys":["com.poemgen.mockspire.poemgenerator"]},{"name":"main()","description":null,"location":"app/com.poemgen.mockspire.poemgenerator/main.html","searchKeys":["main()"]},{"name":"com.poemgen.mockspire.poemgenerator.ai","description":null,"location":"app/com.poemgen.mockspire.poemgenerator.ai/index.html","searchKeys":["com.poemgen.mockspire.poemgenerator.ai"]},{"name":"MockGenerator","description":null,"location":"app/com.poemgen.mockspire.poemgenerator.ai/-mock-generator/index.html","searchKeys":["MockGenerator"]},{"name":"PoemGenerator","description":null,"location":"app/com.poemgen.mockspire.poemgenerator.ai/-poem-generator/index.html","searchKeys":["PoemGenerator"]},{"name":"com.poemgen.mockspire.poemgenerator.controller","description":null,"location":"app/com.poemgen.mockspire.poemgenerator.controller/index.html","searchKeys":["com.poemgen.mockspire.poemgenerator.controller"]},{"name":"PoemManager","description":null,"location":"app/com.poemgen.mockspire.poemgenerator.controller/-poem-manager/index.html","searchKeys":["PoemManager"]},{"name":"com.poemgen.mockspire.poemgenerator.record","description":null,"location":"app/com.poemgen.mockspire.poemgenerator.record/index.html","searchKeys":["com.poemgen.mockspire.poemgenerator.record"]},{"name":"Garden","description":null,"location":"app/com.poemgen.mockspire.poemgenerator.record/-garden/index.html","searchKeys":["Garden"]},{"name":"Leaf","description":null,"location":"app/com.poemgen.mockspire.poemgenerator.record/-leaf/index.html","searchKeys":["Leaf"]}]
